bin/CPC2.py
bin/CPC2_output_peptide.py
bin/__init__.py
bin/compress.py
bin/seqio.py
cpc2_standalone/__init__.py
cpc2_standalone/data/cpc2.model
cpc2_standalone/data/cpc2.range
cpc2_standalone/data/example.fa
cpc2_standalone/libs/libsvm/libsvm-3.18/COPYRIGHT
cpc2_standalone/libs/libsvm/libsvm-3.18/FAQ.html
cpc2_standalone/libs/libsvm/libsvm-3.18/Makefile
cpc2_standalone/libs/libsvm/libsvm-3.18/Makefile.win
cpc2_standalone/libs/libsvm/libsvm-3.18/README
cpc2_standalone/libs/libsvm/libsvm-3.18/heart_scale
cpc2_standalone/libs/libsvm/libsvm-3.18/svm-predict
cpc2_standalone/libs/libsvm/libsvm-3.18/svm-predict.c
cpc2_standalone/libs/libsvm/libsvm-3.18/svm-scale
cpc2_standalone/libs/libsvm/libsvm-3.18/svm-scale.c
cpc2_standalone/libs/libsvm/libsvm-3.18/svm-train
cpc2_standalone/libs/libsvm/libsvm-3.18/svm-train.c
cpc2_standalone/libs/libsvm/libsvm-3.18/svm.cpp
cpc2_standalone/libs/libsvm/libsvm-3.18/svm.def
cpc2_standalone/libs/libsvm/libsvm-3.18/svm.h
cpc2_standalone/libs/libsvm/libsvm-3.18/svm.o
cpc2_standalone/libs/libsvm/libsvm-3.18/java/Makefile
cpc2_standalone/libs/libsvm/libsvm-3.18/java/libsvm.jar
cpc2_standalone/libs/libsvm/libsvm-3.18/java/svm_predict.java
cpc2_standalone/libs/libsvm/libsvm-3.18/java/svm_scale.java
cpc2_standalone/libs/libsvm/libsvm-3.18/java/svm_toy.java
cpc2_standalone/libs/libsvm/libsvm-3.18/java/svm_train.java
cpc2_standalone/libs/libsvm/libsvm-3.18/java/test_applet.html
cpc2_standalone/libs/libsvm/libsvm-3.18/java/libsvm/svm.java
cpc2_standalone/libs/libsvm/libsvm-3.18/java/libsvm/svm.m4
cpc2_standalone/libs/libsvm/libsvm-3.18/java/libsvm/svm_model.java
cpc2_standalone/libs/libsvm/libsvm-3.18/java/libsvm/svm_node.java
cpc2_standalone/libs/libsvm/libsvm-3.18/java/libsvm/svm_parameter.java
cpc2_standalone/libs/libsvm/libsvm-3.18/java/libsvm/svm_print_interface.java
cpc2_standalone/libs/libsvm/libsvm-3.18/java/libsvm/svm_problem.java
cpc2_standalone/libs/libsvm/libsvm-3.18/matlab/Makefile
cpc2_standalone/libs/libsvm/libsvm-3.18/matlab/README
cpc2_standalone-1.0.9.dist-info/licenses/LICENSE
cpc2_standalone-1.0.9.dist-info/METADATA
cpc2_standalone-1.0.9.dist-info/WHEEL
cpc2_standalone-1.0.9.dist-info/entry_points.txt
cpc2_standalone-1.0.9.dist-info/top_level.txt
cpc2_standalone-1.0.9.dist-info/RECORD
