Metadata-Version: 2.4
Name: cpc2_standalone
Version: 1.0.9
Summary: CPC2: A fast and accurate coding potential calculator based on sequence intrinsic features. This package is maintained by Pranjal Pruthi, BioinformaticsOnLine organization.
Home-page: https://github.com/gao-lab/CPC2_standalone
Author: Kang Y. J., Yang D. C., Kong L., Hou M., Meng Y. Q., Wei L., Gao G.
Author-email: gaog@mail.cbi.pku.edu.cn
Maintainer: Pranjal Pruthi
Maintainer-email: mail@pranjal.work
Classifier: Programming Language :: Python :: 3
Classifier: License :: OSI Approved :: GNU General Public License v3 (GPLv3)
Classifier: Operating System :: OS Independent
Classifier: Topic :: Scientific/Engineering :: Bio-Informatics
Classifier: Intended Audience :: Science/Research
Requires-Python: >=3.9,<3.14
License-File: LICENSE
Requires-Dist: numpy
Requires-Dist: biopython
Requires-Dist: six
Dynamic: author
Dynamic: author-email
Dynamic: classifier
Dynamic: description
Dynamic: description-content-type
Dynamic: home-page
Dynamic: license-file
Dynamic: maintainer
Dynamic: maintainer-email
Dynamic: requires-dist
Dynamic: requires-python
Dynamic: summary
